{
  "generatedAt": "2026-05-20T15:57:26.052Z",
  "sources": [
    {
      "name": "9to5Mac",
      "homepage": "https://9to5mac.com"
    },
    {
      "name": "MacRumors",
      "homepage": "https://www.macrumors.com"
    },
    {
      "name": "The Verge",
      "homepage": "https://www.theverge.com"
    },
    {
      "name": "AppleInsider",
      "homepage": "https://appleinsider.com"
    },
    {
      "name": "Six Colors",
      "homepage": "https://sixcolors.com"
    }
  ],
  "items": [
    {
      "source": "AppleInsider",
      "sourceHomepage": "https://appleinsider.com",
      "title": "Latest Apple Immersive rollout exemplifies Apple Vision Pro's entire problem",
      "url": "https://appleinsider.com/articles/26/05/20/latest-apple-immersive-rollout-exemplifies-apple-vision-pros-entire-problem?utm_source=rss",
      "pubDate": "2026-05-20T15:49:52.000Z"
    },
    {
      "source": "MacRumors",
      "sourceHomepage": "https://www.macrumors.com",
      "title": "Samsung Overtakes Apple for Top Smartphone Customer Satisfaction",
      "url": "https://www.macrumors.com/2026/05/20/samsung-overtakes-apple-for-customer-satisfaction/",
      "pubDate": "2026-05-20T15:45:00.000Z"
    },
    {
      "source": "MacRumors",
      "sourceHomepage": "https://www.macrumors.com",
      "title": "Apple Provides Update on App Store, Highlights Key 2025 Safety Stats",
      "url": "https://www.macrumors.com/2026/05/20/apple-shares-app-store-safety-stats/",
      "pubDate": "2026-05-20T15:33:54.000Z"
    },
    {
      "source": "The Verge",
      "sourceHomepage": "https://www.theverge.com",
      "title": "Anker’s travel-friendly Laptop Power Bank has returned to its best price of the year",
      "url": "https://www.theverge.com/gadgets/934288/anker-laptop-power-bank-soundcore-sleep-a20-earbuds-deal-sale",
      "pubDate": "2026-05-20T15:33:08.000Z"
    },
    {
      "source": "9to5Mac",
      "sourceHomepage": "https://9to5mac.com",
      "title": "Deals: M3 iPad Air $400 off, 1TB M5 iPad Pro all-time low, 24GB M5 MacBook Pro $1,499, Apple Watch Ultra 3, more",
      "url": "https://9to5mac.com/2026/05/20/deals-ipad-air-ipad-pro-macbook-pro-apple-watch-ultra-3/",
      "pubDate": "2026-05-20T15:31:27.000Z"
    },
    {
      "source": "AppleInsider",
      "sourceHomepage": "https://appleinsider.com",
      "title": "Apple TV went from industry skepticism to Cannes Lions recognition under Eddy Cue",
      "url": "https://appleinsider.com/articles/26/05/20/apple-tv-went-from-industry-skepticism-to-cannes-lions-recognition-under-eddy-cue?utm_source=rss",
      "pubDate": "2026-05-20T15:13:35.000Z"
    },
    {
      "source": "AppleInsider",
      "sourceHomepage": "https://appleinsider.com",
      "title": "Google I/O 2026 had nothing to say and said it badly ahead of Apple's WWDC",
      "url": "https://appleinsider.com/articles/26/05/20/google-io-2026-had-nothing-to-say-and-said-it-badly-ahead-of-apples-wwdc?utm_source=rss",
      "pubDate": "2026-05-20T15:10:21.000Z"
    },
    {
      "source": "The Verge",
      "sourceHomepage": "https://www.theverge.com",
      "title": "The Verge’s 2026 high school graduation gift guide",
      "url": "https://www.theverge.com/gadgets/932602/best-high-school-graduation-gift-ideas",
      "pubDate": "2026-05-20T15:00:00.000Z"
    },
    {
      "source": "9to5Mac",
      "sourceHomepage": "https://9to5mac.com",
      "title": "Apple’s three goals for iOS 27 sound like a big win for users",
      "url": "https://9to5mac.com/2026/05/20/apples-three-goals-for-ios-27-sound-like-a-big-win-for-users/",
      "pubDate": "2026-05-20T14:49:32.000Z"
    },
    {
      "source": "MacRumors",
      "sourceHomepage": "https://www.macrumors.com",
      "title": "Ugreen Debuts Pocket-Sized Chargers for Your Apple Devices",
      "url": "https://www.macrumors.com/2026/05/20/ugreen-65w-charger-macbook-air/",
      "pubDate": "2026-05-20T14:42:57.000Z"
    },
    {
      "source": "The Verge",
      "sourceHomepage": "https://www.theverge.com",
      "title": "A feature-packed MagSafe power bank is 20 percent off for Memorial Day",
      "url": "https://www.theverge.com/gadgets/934553/anker-magsafe-power-bank-usbc-deal-sale-memorial-day",
      "pubDate": "2026-05-20T14:14:00.000Z"
    },
    {
      "source": "The Verge",
      "sourceHomepage": "https://www.theverge.com",
      "title": "It&#8217;s make or break time for AI labeling systems",
      "url": "https://www.theverge.com/ai-artificial-intelligence/934521/google-synthid-c2pa-content-credentials-ai-labelling-efforts",
      "pubDate": "2026-05-20T14:12:54.000Z"
    },
    {
      "source": "AppleInsider",
      "sourceHomepage": "https://appleinsider.com",
      "title": "App Store fraud prevention a big numbers game powered by AI & human review",
      "url": "https://appleinsider.com/articles/26/05/20/app-store-fraud-prevention-a-big-numbers-game-powered-by-ai-human-review?utm_source=rss",
      "pubDate": "2026-05-20T14:09:20.000Z"
    },
    {
      "source": "The Verge",
      "sourceHomepage": "https://www.theverge.com",
      "title": "Trump Mobile may be leaking customer addresses",
      "url": "https://www.theverge.com/gadgets/934522/trump-mobile-may-be-leaking-customer-addresses",
      "pubDate": "2026-05-20T14:06:19.000Z"
    },
    {
      "source": "The Verge",
      "sourceHomepage": "https://www.theverge.com",
      "title": "Insta360’s Mic Pro uses a three microphone array for improved recordings",
      "url": "https://www.theverge.com/tech/934473/insta360-mic-pro-wireless-e-ink-screen-microphone-array",
      "pubDate": "2026-05-20T14:04:42.000Z"
    },
    {
      "source": "The Verge",
      "sourceHomepage": "https://www.theverge.com",
      "title": "Trump is waging a silent war on legal immigration",
      "url": "https://www.theverge.com/policy/932865/trump-legal-immigration-denaturalizations-uscis",
      "pubDate": "2026-05-20T14:00:00.000Z"
    },
    {
      "source": "MacRumors",
      "sourceHomepage": "https://www.macrumors.com",
      "title": "Apple's Eddy Cue to Receive 'Entertainment Person of the Year' Award",
      "url": "https://www.macrumors.com/2026/05/20/eddy-cue-entertainment-person-of-the-year/",
      "pubDate": "2026-05-20T13:57:50.000Z"
    },
    {
      "source": "MacRumors",
      "sourceHomepage": "https://www.macrumors.com",
      "title": "Amazon Takes $150 Off Every 15-Inch M5 MacBook Air",
      "url": "https://www.macrumors.com/2026/05/20/150-off-m5-macbook-air/",
      "pubDate": "2026-05-20T13:38:56.000Z"
    },
    {
      "source": "9to5Mac",
      "sourceHomepage": "https://9to5mac.com",
      "title": "Apple gives update on the App Store and its key protections",
      "url": "https://9to5mac.com/2026/05/20/apple-gives-update-on-the-app-store-and-its-key-protections/",
      "pubDate": "2026-05-20T13:28:31.000Z"
    },
    {
      "source": "The Verge",
      "sourceHomepage": "https://www.theverge.com",
      "title": "If Google can’t make AI agents useful, maybe no one can",
      "url": "https://www.theverge.com/ai-artificial-intelligence/934478/if-google-cant-make-ai-agents-useful-maybe-no-one-can",
      "pubDate": "2026-05-20T13:24:22.000Z"
    },
    {
      "source": "9to5Mac",
      "sourceHomepage": "https://9to5mac.com",
      "title": "New ‘Steve Jobs in Exile’ book reads like a lost season of your favorite series",
      "url": "https://9to5mac.com/2026/05/20/new-steve-jobs-in-exile-book-reads-like-a-lost-season-of-your-favorite-series/",
      "pubDate": "2026-05-20T13:06:17.000Z"
    },
    {
      "source": "9to5Mac",
      "sourceHomepage": "https://9to5mac.com",
      "title": "AI companies and data brokers even resort to fake forms to keep selling our data",
      "url": "https://9to5mac.com/2026/05/20/ai-companies-and-data-brokers-even-resort-to-fake-forms-to-keep-selling-our-data/",
      "pubDate": "2026-05-20T13:01:30.000Z"
    },
    {
      "source": "9to5Mac",
      "sourceHomepage": "https://9to5mac.com",
      "title": "Apple Immersive video on Real Madrid coming this week to Vision Pro",
      "url": "https://9to5mac.com/2026/05/20/apple-immersive-video-on-real-madrid-coming-this-week-to-vision-pro/",
      "pubDate": "2026-05-20T13:00:00.000Z"
    },
    {
      "source": "The Verge",
      "sourceHomepage": "https://www.theverge.com",
      "title": "The biggest data center ever is becoming a huge problem in Utah",
      "url": "https://www.theverge.com/ai-artificial-intelligence/933687/utah-stratos-project-data-center-kevin-oleary",
      "pubDate": "2026-05-20T13:00:00.000Z"
    },
    {
      "source": "9to5Mac",
      "sourceHomepage": "https://9to5mac.com",
      "title": "Jamf names former CTO Beth Tschida as CEO to lead its new AI push",
      "url": "https://9to5mac.com/2026/05/20/jamf-names-former-cto-beth-tschida-as-ceo-to-lead-its-new-ai-push/",
      "pubDate": "2026-05-20T12:00:00.000Z"
    },
    {
      "source": "The Verge",
      "sourceHomepage": "https://www.theverge.com",
      "title": "‘It’s in the air’: Apple TV’s hottest new shows explore different sides of OnlyFans",
      "url": "https://www.theverge.com/tech/934078/apple-tv-onlyfans-margo-maximum-pleasure-guaranteed",
      "pubDate": "2026-05-20T12:00:00.000Z"
    },
    {
      "source": "9to5Mac",
      "sourceHomepage": "https://9to5mac.com",
      "title": "Android cloning Apple’s Handoff feature is cheeky but a good thing",
      "url": "https://9to5mac.com/2026/05/20/android-cloning-apples-handoff-feature-is-cheeky-but-a-good-thing/",
      "pubDate": "2026-05-20T11:44:20.000Z"
    },
    {
      "source": "MacRumors",
      "sourceHomepage": "https://www.macrumors.com",
      "title": "Discord Voice and Video Calls Now End-to-End Encrypted by Default",
      "url": "https://www.macrumors.com/2026/05/20/discord-voice-video-calls-e2ee-default/",
      "pubDate": "2026-05-20T11:43:34.000Z"
    },
    {
      "source": "9to5Mac",
      "sourceHomepage": "https://9to5mac.com",
      "title": "Discord now uses end-to-end encryption for all voice and video calls by default",
      "url": "https://9to5mac.com/2026/05/20/discord-now-uses-end-to-end-encryption-for-all-voice-and-video-calls-by-default/",
      "pubDate": "2026-05-20T11:08:28.000Z"
    },
    {
      "source": "9to5Mac",
      "sourceHomepage": "https://9to5mac.com",
      "title": "9to5Mac Daily: May 20, 2026 – New Apple accessibility features, Apple Watch rumors",
      "url": "https://9to5mac.com/2026/05/20/daily-may-20-2026/",
      "pubDate": "2026-05-20T11:00:00.000Z"
    },
    {
      "source": "MacRumors",
      "sourceHomepage": "https://www.macrumors.com",
      "title": "WhatsApp Tests Read-Triggered Disappearing Messages",
      "url": "https://www.macrumors.com/2026/05/20/read-triggered-disappearing-messages-whatsapp/",
      "pubDate": "2026-05-20T10:57:37.000Z"
    },
    {
      "source": "AppleInsider",
      "sourceHomepage": "https://appleinsider.com",
      "title": "Insta360 Mic Pro review: exceptional sound quality for a wireless microphone",
      "url": "https://appleinsider.com/articles/26/05/20/insta360-pro-mic-review-exceptional-sound-quality-for-a-wireless-microphone?utm_source=rss",
      "pubDate": "2026-05-20T07:29:53.000Z"
    },
    {
      "source": "Six Colors",
      "sourceHomepage": "https://sixcolors.com",
      "title": "Apple Sports expands, readies for World Cup ↦",
      "url": "https://sixcolors.com/link/2026/05/apple-sports-expands-readies-for-world-cup/",
      "pubDate": "2026-05-20T05:01:55.000Z"
    },
    {
      "source": "9to5Mac",
      "sourceHomepage": "https://9to5mac.com",
      "title": "‘Maximum Pleasure Guaranteed’ premieres on Apple TV",
      "url": "https://9to5mac.com/2026/05/19/maximum-pleasure-guaranteed-premieres-on-apple-tv/",
      "pubDate": "2026-05-20T02:27:26.000Z"
    },
    {
      "source": "9to5Mac",
      "sourceHomepage": "https://9to5mac.com",
      "title": "WhatsApp working on messages that disappear once you’ve read them",
      "url": "https://9to5mac.com/2026/05/19/whatsapp-working-on-messages-that-disappear-once-youve-read-them/",
      "pubDate": "2026-05-20T01:56:34.000Z"
    },
    {
      "source": "MacRumors",
      "sourceHomepage": "https://www.macrumors.com",
      "title": "Plex Tripling Lifetime Plex Pass Price to $750 in July",
      "url": "https://www.macrumors.com/2026/05/19/lifetime-plex-pass-price-increase/",
      "pubDate": "2026-05-19T22:53:39.000Z"
    },
    {
      "source": "AppleInsider",
      "sourceHomepage": "https://appleinsider.com",
      "title": "Nintendo announces 'Pictonico!', a collection of minigames powered by your photos",
      "url": "https://appleinsider.com/articles/26/05/19/nintendo-announces-pictonico-a-collection-of-minigames-powered-by-your-photos?utm_source=rss",
      "pubDate": "2026-05-19T22:31:13.000Z"
    },
    {
      "source": "MacRumors",
      "sourceHomepage": "https://www.macrumors.com",
      "title": "Google's First AI Smart Glasses Launching This Fall With iPhone Support",
      "url": "https://www.macrumors.com/2026/05/19/google-ai-smart-glasses-iphone-support/",
      "pubDate": "2026-05-19T21:34:12.000Z"
    },
    {
      "source": "Six Colors",
      "sourceHomepage": "https://sixcolors.com",
      "title": "Take Control live course helps you conquer Big Tech ↦",
      "url": "https://sixcolors.com/link/2026/05/take-control-live-course-helps-you-conquer-big-tech/",
      "pubDate": "2026-05-19T21:10:00.000Z"
    },
    {
      "source": "MacRumors",
      "sourceHomepage": "https://www.macrumors.com",
      "title": "Apple Taps Virtual Avatar Firm Animato's Expertise and Intellectual Property",
      "url": "https://www.macrumors.com/2026/05/19/apple-acquires-animato/",
      "pubDate": "2026-05-19T21:02:18.000Z"
    },
    {
      "source": "MacRumors",
      "sourceHomepage": "https://www.macrumors.com",
      "title": "Nintendo's New 'Pictonico' iOS Game Turns Your Photos Into Minigames",
      "url": "https://www.macrumors.com/2026/05/19/nintendo-pictonico-ios-game/",
      "pubDate": "2026-05-19T20:25:47.000Z"
    },
    {
      "source": "AppleInsider",
      "sourceHomepage": "https://appleinsider.com",
      "title": "Vibe Coding: Where it works and why doing it on an iPhone is a problem",
      "url": "https://appleinsider.com/articles/26/05/19/vibe-coding-where-it-works-and-why-doing-it-on-an-iphone-is-a-problem?utm_source=rss",
      "pubDate": "2026-05-19T19:30:45.000Z"
    },
    {
      "source": "MacRumors",
      "sourceHomepage": "https://www.macrumors.com",
      "title": "Google I/O 2026 Roundup: Gemini 3.5, AI Search, Android XR Glasses, and More",
      "url": "https://www.macrumors.com/2026/05/19/google-io-2026-roundup/",
      "pubDate": "2026-05-19T19:04:45.000Z"
    },
    {
      "source": "AppleInsider",
      "sourceHomepage": "https://appleinsider.com",
      "title": "Peanuts classics, returning series, and a new Snoopy film are all coming to Apple TV",
      "url": "https://appleinsider.com/articles/26/05/19/peanuts-classics-returning-series-and-a-new-snoopy-film-are-all-coming-to-apple-tv?utm_source=rss",
      "pubDate": "2026-05-19T18:24:11.000Z"
    },
    {
      "source": "AppleInsider",
      "sourceHomepage": "https://appleinsider.com",
      "title": "Easily follow the FIFA World Cup in over 170 countries thanks to Apple Sports expansion",
      "url": "https://appleinsider.com/articles/26/05/19/easily-follow-the-ffia-world-cup-in-over-170-countries-thanks-to-apple-sports-expansion?utm_source=rss",
      "pubDate": "2026-05-19T17:17:17.000Z"
    },
    {
      "source": "AppleInsider",
      "sourceHomepage": "https://appleinsider.com",
      "title": "Second hardware team shakeup in a month seeks to speed up development",
      "url": "https://appleinsider.com/articles/26/05/19/second-hardware-team-shakeup-in-a-month-seeks-to-speed-up-development?utm_source=rss",
      "pubDate": "2026-05-19T16:48:58.000Z"
    },
    {
      "source": "AppleInsider",
      "sourceHomepage": "https://appleinsider.com",
      "title": "Amazon slashes $250 off every 2026 16-inch MacBook Pro it sells",
      "url": "https://appleinsider.com/articles/26/05/19/amazon-slashes-250-off-every-2026-16-inch-macbook-pro-it-sells?utm_source=rss",
      "pubDate": "2026-05-19T16:07:44.000Z"
    },
    {
      "source": "Six Colors",
      "sourceHomepage": "https://sixcolors.com",
      "title": "New Apple accessibility updates focus on Apple Intelligence",
      "url": "https://sixcolors.com/post/2026/05/new-apple-accessibility-updates-focus-on-apple-intelligence/",
      "pubDate": "2026-05-19T12:00:00.000Z"
    },
    {
      "source": "Six Colors",
      "sourceHomepage": "https://sixcolors.com",
      "title": "(Podcast) Upgrade 616: Outmoded But Not Vintage",
      "url": "https://sixcolors.com/podcast/2026/05/upgrade-616-outmoded-but-not-vintage/",
      "pubDate": "2026-05-18T22:05:38.000Z"
    },
    {
      "source": "Six Colors",
      "sourceHomepage": "https://sixcolors.com",
      "title": "FileVault keys can’t be escrowed in iCloud anymore",
      "url": "https://sixcolors.com/post/2026/05/filevault-keys-cant-be-escrowed-in-icloud-anymore/",
      "pubDate": "2026-05-18T17:00:22.000Z"
    }
  ]
}
